tap_redshift/__init__.py
tap_redshift/resolve.py
tap_redshift-1.0.0b9.dist-info/METADATA
tap_redshift-1.0.0b9.dist-info/RECORD
tap_redshift-1.0.0b9.dist-info/WHEEL
tap_redshift-1.0.0b9.dist-info/entry_points.txt
tap_redshift-1.0.0b9.dist-info/top_level.txt
