Metadata-Version: 2.1
Name: tap-redshift
Version: 1.0.0b9
Summary: Singer.io tap for extracting data from redshift
Home-page: UNKNOWN
Author: data.world
Author-email: help@data.world
License: UNKNOWN
Platform: UNKNOWN
Classifier: Programming Language :: Python :: 3 :: Only
Requires-Dist: attrs (==18.2.0)
Requires-Dist: pendulum (==1.2.0)
Requires-Dist: singer-python (==5.0.4)
Requires-Dist: backoff (==1.3.2)
Requires-Dist: psycopg2 (==2.7.3.2)
